mainline/__init__.py
mainline/catalog.py
mainline/di.py
mainline/exceptions.py
mainline/injection.py
mainline/provider.py
mainline/scope.py
mainline/utils.py
mainline-1.1.0.dist-info/AUTHORS
mainline-1.1.0.dist-info/LICENSE.md
mainline-1.1.0.dist-info/METADATA
mainline-1.1.0.dist-info/WHEEL
mainline-1.1.0.dist-info/pbr.json
mainline-1.1.0.dist-info/top_level.txt
mainline-1.1.0.dist-info/RECORD
