Metadata-Version: 2.1
Name: mainline
Version: 1.1.0
Summary: Simple yet powerful python dependency injection for py2/py3k
Home-page: https://github.com/akatrevorjay/mainline
Author: Trevor Joynson
Author-email: github@skywww.net
License: GPL
Keywords: dependency,injection,ioc
Platform: UNKNOWN
Classifier: Development Status :: 5 - Production/Stable
Classifier: Intended Audience :: Developers
Classifier: Intended Audience :: Information Technology
Classifier: License :: OSI Approved :: GNU General Public License (GPL)
Classifier: Operating System :: OS Independent
Classifier: Programming Language :: Python
Classifier: Topic :: Software Development
Classifier: Topic :: Software Development :: Libraries
Requires-Dist: wrapt
Requires-Dist: six
Provides-Extra: docs
Requires-Dist: sphinx ; extra == 'docs'
Provides-Extra: tests
Requires-Dist: pytest ; extra == 'tests'
Requires-Dist: mock ; extra == 'tests'
Requires-Dist: coveralls ; extra == 'tests'
